{
  "instance_methods": [
    {
      "version": "v1.5.0-rc1",
      "type": "instancemethod",
      "name": "_resolveParam"
    },
    {
      "version": "v1.5.0-rc1",
      "type": "instancemethod",
      "name": "extractParamMap"
    },
    {
      "version": "v1.5.0-rc1",
      "type": "instancemethod",
      "name": "explainParams"
    },
    {
      "version": "v1.5.0-rc1",
      "type": "instancemethod",
      "name": "hasParam"
    },
    {
      "version": "v1.5.0-rc1",
      "type": "instancemethod",
      "name": "hasDefault"
    },
    {
      "version": "v1.5.0-rc1",
      "type": "instancemethod",
      "name": "isDefined"
    },
    {
      "version": "v1.5.0-rc1",
      "type": "instancemethod",
      "name": "_copyValues"
    },
    {
      "version": "v1.5.0-rc1",
      "type": "instancemethod",
      "name": "explainParam"
    },
    {
      "version": "v1.5.0-rc1",
      "type": "instancemethod",
      "name": "_shouldOwn"
    },
    {
      "version": "v1.5.0-rc1",
      "type": "instancemethod",
      "name": "_set"
    },
    {
      "version": "v1.5.0-rc1",
      "type": "instancemethod",
      "name": "getParam"
    },
    {
      "version": "v1.5.0-rc1",
      "type": "property",
      "name": "params"
    },
    {
      "version": "v1.5.0-rc1",
      "type": "instancemethod",
      "name": "getOrDefault"
    },
    {
      "version": "v1.5.0-rc1",
      "type": "instancemethod",
      "name": "copy"
    },
    {
      "version": "v1.5.0-rc1",
      "type": "instancemethod",
      "name": "isSet"
    },
    {
      "version": "v1.5.0-rc1",
      "type": "instancemethod",
      "name": "_setDefault"
    }
  ],
  "version": "v1.5.0-rc1",
  "name": "pyspark.ml.clustering.Params",
  "class_methods": [
    {
      "version": "v1.5.0-rc1",
      "type": "function",
      "name": "_dummy"
    }
  ]
}