{"MatrixFactorizationModel": {"name": "pyspark.mllib.recommendation.MatrixFactorizationModel", "class_methods": {}, "instance_methods": {}}, "SparkContext": {"name": "pyspark.mllib.recommendation.SparkContext", "class_methods": {}, "instance_methods": {}}, "JavaLoader": {"name": "pyspark.mllib.recommendation.JavaLoader", "class_methods": {}, "instance_methods": {}}, "DataFrame": {"name": "pyspark.mllib.recommendation.DataFrame", "class_methods": {}, "instance_methods": {}}, "JavaModelWrapper": {"name": "pyspark.mllib.recommendation.JavaModelWrapper", "class_methods": {}, "instance_methods": {}}, "ALS": {"name": "pyspark.mllib.recommendation.ALS", "class_methods": {}, "instance_methods": {}}, "Rating": {"name": "pyspark.mllib.recommendation.Rating", "class_methods": {}, "instance_methods": {}}, "RDD": {"name": "pyspark.mllib.recommendation.RDD", "class_methods": {}, "instance_methods": {}}, "JavaSaveable": {"name": "pyspark.mllib.recommendation.JavaSaveable", "class_methods": {}, "instance_methods": {}}}
