{"SparseVector": {"instance_methods": {}, "name": "SparseVector", "class_methods": {"squared_distance": {"argspec": ["self", "other"], "name": "squared_distance"}, "dot": {"argspec": ["self", "other"], "name": "dot"}}}, "LabeledPoint": {"instance_methods": {}, "name": "LabeledPoint", "class_methods": {}}, "Vectors": {"instance_methods": {}, "name": "Vectors", "class_methods": {"dense": {"argspec": ["elements"], "name": "dense"}, "sparse": {"argspec": ["size"], "name": "sparse"}}}, "MLUtils": {"instance_methods": {}, "name": "MLUtils", "class_methods": {"_convert_labeled_point_to_libsvm": {"argspec": ["p"], "name": "_convert_labeled_point_to_libsvm"}, "loadLibSVMFile": {"argspec": ["sc", "path", "multiclass", "numFeatures", "minPartitions"], "name": "loadLibSVMFile"}, "saveAsLibSVMFile": {"argspec": ["data", "dir"], "name": "saveAsLibSVMFile"}, "_parse_libsvm_line": {"argspec": ["line", "multiclass"], "name": "_parse_libsvm_line"}}}}
